tfcommander/__about__.py
tfcommander/__init__.py
tfcommander/__main__.py
tfcommander/__main__.py.bak
tfcommander/tf5.py
tfcommander/tf6.py
tfcommander-0.1.20.dist-info/METADATA
tfcommander-0.1.20.dist-info/WHEEL
tfcommander-0.1.20.dist-info/entry_points.txt
tfcommander-0.1.20.dist-info/licenses/LICENSE
tfcommander-0.1.20.dist-info/RECORD
