Metadata-Version: 2.4
Name: tfcommander
Version: 0.1.20
Summary: A simple TraeFik CLI tool
Author-email: Jakub Jim Zacek <jakub@zacekj.cz>
License-Expression: MIT
License-File: LICENSE
Requires-Python: >=3.8
Requires-Dist: requests
Requires-Dist: tabulate
